setup.cfg
setup.py
serializers/__init__.py
serializers/consts.py
serializers/factory.py
serializers/packing_tool.py
serializers/serializer.py
serializers/serializer_json.py
serializers/serializer_xml.py
xml_json_serializer2.egg-info/PKG-INFO
xml_json_serializer2.egg-info/SOURCES.txt
xml_json_serializer2.egg-info/dependency_links.txt
xml_json_serializer2.egg-info/requires.txt
xml_json_serializer2.egg-info/top_level.txt